jupytery_react/__init__.py
jupytery_react/__main__.py
jupytery_react/application.py
jupytery_react/handlers.py
jupytery_react/static/favicon.ico
jupytery_react/static/plotly-2.3.0.min.js
jupytery_react/templates/error.html
jupytery_react/templates/page.html
jupytery_react-0.0.6.data/data/etc/jupyter/jupyter_server_config.d/jupytery_react.json
jupytery_react-0.0.6.data/data/jupytery_react/static/favicon.ico
jupytery_react-0.0.6.data/data/jupytery_react/static/plotly-2.3.0.min.js
jupytery_react-0.0.6.data/data/jupytery_react/templates/error.html
jupytery_react-0.0.6.data/data/jupytery_react/templates/page.html
jupytery_react-0.0.6.dist-info/LICENSE
jupytery_react-0.0.6.dist-info/METADATA
jupytery_react-0.0.6.dist-info/WHEEL
jupytery_react-0.0.6.dist-info/entry_points.txt
jupytery_react-0.0.6.dist-info/top_level.txt
jupytery_react-0.0.6.dist-info/RECORD
