Metadata-Version: 2.1
Name: jupytery-react
Version: 0.0.6
Summary: Jupytery React
Home-page: UNKNOWN
License: UNKNOWN
Platform: UNKNOWN
Requires-Python: >=3.8
License-File: LICENSE
Requires-Dist: jupyter-server
Requires-Dist: jinja2
Provides-Extra: test
Requires-Dist: pytest ; extra == 'test'
